showermodel/__init__.py
showermodel/_dev_version.py
showermodel/_tools.py
showermodel/_version.py
showermodel/atmosphere.py
showermodel/cherenkov.py
showermodel/event.py
showermodel/fluorescence.py
showermodel/image.py
showermodel/observatory.py
showermodel/profile.py
showermodel/projection.py
showermodel/shower.py
showermodel/signal.py
showermodel/telescope.py
showermodel/track.py
showermodel/version.py
ShowerModel-0.1.9.dist-info/LICENSE
ShowerModel-0.1.9.dist-info/METADATA
ShowerModel-0.1.9.dist-info/WHEEL
ShowerModel-0.1.9.dist-info/top_level.txt
ShowerModel-0.1.9.dist-info/RECORD
