Metadata-Version: 2.1
Name: ShowerModel
Version: 0.1.9
Summary: Modelling cosmic-ray showers, their light production and its detection
Home-page: https://github.com/JaimeRosado/ShowerModel
Author: Jaime Rosado
Author-email: jrosadov@ucm.es
License: GPL-3.0
Classifier: Intended Audience :: Science/Research
Classifier: License :: OSI Approved :: BSD License
Classifier: Programming Language :: Python :: 3
Classifier: Programming Language :: Python :: 3.7
Classifier: Programming Language :: Python :: 3.8
Classifier: Programming Language :: Python :: 3.9
Classifier: Topic :: Scientific/Engineering :: Astronomy
Requires-Python: >=3.7
License-File: LICENSE
Requires-Dist: numpy
Requires-Dist: pandas
Requires-Dist: matplotlib
Requires-Dist: scipy
Requires-Dist: ipython
Requires-Dist: setuptools-scm
Provides-Extra: docs
Requires-Dist: sphinx-rtd-theme ; extra == 'docs'
Requires-Dist: sphinx-automodapi ; extra == 'docs'
Requires-Dist: sphinx ; extra == 'docs'
Requires-Dist: nbsphinx ; extra == 'docs'
Requires-Dist: nbsphinx-link ; extra == 'docs'
Requires-Dist: numpydoc ; extra == 'docs'
Requires-Dist: jupyter ; extra == 'docs'
Requires-Dist: notebook ; extra == 'docs'
Requires-Dist: graphviz ; extra == 'docs'
